softclip/__init__.py
softclip/softclip.py
softclip-0.1.0.dist-info/LICENSE
softclip-0.1.0.dist-info/METADATA
softclip-0.1.0.dist-info/WHEEL
softclip-0.1.0.dist-info/top_level.txt
softclip-0.1.0.dist-info/RECORD
